[{"domain": "www.zhihu.com", "expiry": 1547102380.854605, "httpOnly": false, "name": "tgw_l7_route", "path": "/", "secure": false, "value": "7bacb9af7224ed68945ce419f4dea76d"}, {"domain": ".zhihu.com", "expiry": 1641709496.739906, "httpOnly": false, "name": "q_c1", "path": "/", "secure": false, "value": "5e24b5984b1244e389c2121807ed905e|1547101495000|1547101495000"}, {"domain": ".zhihu.com", "expiry": 1549693495.445762, "httpOnly": true, "name": "z_c0", "path": "/", "secure": false, "value": "\"2|1:0|10:1547101494|4:z_c0|92:Mi4xeDFyaURRQUFBQUFBMEtDVmRLX05EaWNBQUFDRUFsVk5ObkplWEFBV1lGX0RZZGFrdUU1M0JwMllCV09FTG1XRjRB|1621125079e47128d610f33b59fcb035dac7e12a9e1299cee5de7a06c8729996\""}, {"domain": ".zhihu.com", "expiry": 1610173480.85472, "httpOnly": false, "name": "_zap", "path": "/", "secure": false, "value": "ef183162-d643-486b-84fe-46fa9ccff765"}, {"domain": ".zhihu.com", "expiry": 1641709481.510044, "httpOnly": false, "name": "d_c0", "path": "/", "secure": false, "value": "\"AMCjpnSvzQ6PTi1icA5xsmsfKH-EnxJ6qAU=|1547101480\""}, {"domain": ".zhihu.com", "httpOnly": false, "name": "_xsrf", "path": "/", "secure": false, "value": "9d026be0-d6e7-403b-9c8f-c1594cdfa254"}, {"domain": ".zhihu.com", "expiry": 1549693481.620659, "httpOnly": true, "name": "capsion_ticket", "path": "/", "secure": false, "value": "\"2|1:0|10:1547101480|14:capsion_ticket|44:MzQyOWJhYTA3NTYwNGM0OWE3ZjNiODA4ZDIxMThjNDk=|bb1b46b861139f0a797faeda7ffb2c194b42af4f33a3c690f28f93af08552d84\""}, {"domain": ".zhihu.com", "expiry": 1549693496, "httpOnly": false, "name": "tst", "path": "/", "secure": false, "value": "r"}]